setup.py
quantum_queen.egg-info/PKG-INFO
quantum_queen.egg-info/SOURCES.txt
quantum_queen.egg-info/dependency_links.txt
quantum_queen.egg-info/requires.txt
quantum_queen.egg-info/top_level.txt
queen/__init__.py
queen/ext/__init__.py
queen/ext/awx/__init__.py
queen/ext/awx/client.py
queen/ext/awx/ansible/__init__.py
queen/ext/awx/ansible/base.py
queen/ext/awx/ansible/credential.py
queen/ext/awx/ansible/credentialtype.py
queen/ext/awx/ansible/inventory.py
queen/ext/awx/ansible/inventorygroup.py
queen/ext/awx/ansible/inventoryhost.py
queen/ext/awx/ansible/jobtemplate.py
queen/ext/awx/ansible/jobtemplatecredential.py
queen/ext/awx/ansible/lookup.py
queen/ext/awx/ansible/project.py
queen/ext/awx/ansible/schema.py
queen/ext/awx/ansible/team.py
queen/ext/awx/ansible/user.py
queen/lib/__init__.py
queen/lib/ansible.py
queen/lib/api.py