Metadata-Version: 1.0
Name: quantum-queen
Version: 1.0.10
Summary: Unimatrix One Provisioning Library (Quantum Queen)
Home-page: https://www.wizardsofindustry.com
Author: Cochise Ruhulessin
Author-email: cochise.ruhulessin@wizardsofindustry.com
License: UNKNOWN
Platform: UNKNOWN
